{"build":1008,"name":"PIA","pools":[{"id":"us-california","name":"US California","country":"US","hostname":"us-california.privateinternetaccess.com","addrs":[]},{"id":"us-east","name":"US East","country":"US","hostname":"us-east.privateinternetaccess.com","addrs":[]},{"id":"us-midwest","name":"US Midwest","country":"US","hostname":"us-midwest.privateinternetaccess.com","addrs":[]},{"id":"us-chicago","name":"US Chicago","country":"US","hostname":"us-chicago.privateinternetaccess.com","addrs":[]},{"id":"us-texas","name":"US Texas","country":"US","hostname":"us-texas.privateinternetaccess.com","addrs":[]},{"id":"us-florida","name":"US Florida","country":"US","hostname":"us-florida.privateinternetaccess.com","addrs":[]},{"id":"us-seattle","name":"US Seattle","country":"US","hostname":"us-seattle.privateinternetaccess.com","addrs":[]},{"id":"us-west","name":"US West","country":"US","hostname":"us-west.privateinternetaccess.com","addrs":[]},{"id":"us-siliconvalley","name":"US Silicon Valley","country":"US","hostname":"us-siliconvalley.privateinternetaccess.com","addrs":[]},{"id":"us-newyorkcity","name":"US New York City","country":"US","hostname":"us-newyorkcity.privateinternetaccess.com","addrs":[]},{"id":"us-washingtondc","name":"US Washington DC","country":"US","hostname":"us-washingtondc.privateinternetaccess.com","addrs":[]},{"id":"us-atlanta","name":"US Atlanta","country":"US","hostname":"us-atlanta.privateinternetaccess.com","addrs":[]},{"id":"us-lasvegas","name":"US Las Vegas","country":"US","hostname":"us-lasvegas.privateinternetaccess.com","addrs":[]},{"id":"us-houston","name":"US Houston","country":"US","hostname":"us-houston.privateinternetaccess.com","addrs":[]},{"id":"us-denver","name":"US Denver","country":"US","hostname":"us-denver.privateinternetaccess.com","addrs":[]},{"id":"uk-london","name":"UK London","country":"GB","hostname":"uk-london.privateinternetaccess.com","addrs":[]},{"id":"uk-southampton","name":"UK Southampton","country":"GB","hostname":"uk-southampton.privateinternetaccess.com","addrs":[]},{"id":"uk-manchester","name":"UK Manchester","country":"GB","hostname":"uk-manchester.privateinternetaccess.com","addrs":[]},{"id":"ca-toronto","name":"CA Toronto","country":"CA","hostname":"ca-toronto.privateinternetaccess.com","addrs":[]},{"id":"ca-montreal","name":"CA Montreal","country":"CA","hostname":"ca-montreal.privateinternetaccess.com","addrs":[]},{"id":"ca-vancouver","name":"CA Vancouver","country":"CA","hostname":"ca-vancouver.privateinternetaccess.com","addrs":[]},{"id":"au-sydney","name":"AU Sydney","country":"AU","hostname":"au-sydney.privateinternetaccess.com","addrs":[]},{"id":"au-melbourne","name":"AU Melbourne","country":"AU","hostname":"au-melbourne.privateinternetaccess.com","addrs":[]},{"id":"de-berlin","name":"DE Berlin","country":"DE","hostname":"de-berlin.privateinternetaccess.com","addrs":[]},{"id":"de-frankfurt","name":"DE Frankfurt","country":"DE","hostname":"de-frankfurt.privateinternetaccess.com","addrs":[]},{"id":"nz","name":"New Zealand","country":"NZ","hostname":"nz.privateinternetaccess.com","addrs":[]},{"id":"nl","name":"Netherlands","country":"NL","hostname":"nl.privateinternetaccess.com","addrs":[]},{"id":"sweden","name":"Sweden","country":"SE","hostname":"sweden.privateinternetaccess.com","addrs":[]},{"id":"no","name":"Norway","country":"NO","hostname":"no.privateinternetaccess.com","addrs":[]},{"id":"denmark","name":"Denmark","country":"DK","hostname":"denmark.privateinternetaccess.com","addrs":[]},{"id":"fi","name":"Finland","country":"FI","hostname":"fi.privateinternetaccess.com","addrs":[]},{"id":"swiss","name":"Switzerland","country":"CH","hostname":"swiss.privateinternetaccess.com","addrs":[]},{"id":"france","name":"France","country":"FR","hostname":"france.privateinternetaccess.com","addrs":[]},{"id":"belgium","name":"Belgium","country":"BE","hostname":"belgium.privateinternetaccess.com","addrs":[]},{"id":"austria","name":"Austria","country":"AT","hostname":"austria.privateinternetaccess.com","addrs":[]},{"id":"czech","name":"Czech Republic","country":"CZ","hostname":"czech.privateinternetaccess.com","addrs":[]},{"id":"lu","name":"Luxembourg","country":"LU","hostname":"lu.privateinternetaccess.com","addrs":[]},{"id":"ireland","name":"Ireland","country":"IE","hostname":"ireland.privateinternetaccess.com","addrs":[]},{"id":"italy","name":"Italy","country":"IT","hostname":"italy.privateinternetaccess.com","addrs":[]},{"id":"spain","name":"Spain","country":"ES","hostname":"spain.privateinternetaccess.com","addrs":[]},{"id":"ro","name":"Romania","country":"RO","hostname":"ro.privateinternetaccess.com","addrs":[]},{"id":"hungary","name":"Hungary","country":"HU","hostname":"hungary.privateinternetaccess.com","addrs":[]},{"id":"poland","name":"Poland","country":"PL","hostname":"poland.privateinternetaccess.com","addrs":[]},{"id":"turkey","name":"Turkey","country":"TR","hostname":"turkey.privateinternetaccess.com","addrs":[]},{"id":"ae","name":"UAE","country":"AE","hostname":"ae.privateinternetaccess.com","addrs":[]},{"id":"hk","name":"Hong Kong","country":"HK","hostname":"hk.privateinternetaccess.com","addrs":[]},{"id":"sg","name":"Singapore","country":"SG","hostname":"sg.privateinternetaccess.com","addrs":[]},{"id":"japan","name":"Japan","country":"JP","hostname":"japan.privateinternetaccess.com","addrs":[]},{"id":"israel","name":"Israel","country":"IL","hostname":"israel.privateinternetaccess.com","addrs":[]},{"id":"mexico","name":"Mexico","country":"MX","hostname":"mexico.privateinternetaccess.com","addrs":[]},{"id":"brazil","name":"Brazil","country":"BR","hostname":"brazil.privateinternetaccess.com","addrs":[]},{"id":"in","name":"India","country":"IN","hostname":"in.privateinternetaccess.com","addrs":[]},{"id":"za","name":"South Africa","country":"ZA","hostname":"za.privateinternetaccess.com","addrs":[]}],"presets":[{"id":"recommended","name":"Recommended","comment":"128-bit encryption","cfg":{"ep":["UDP:1194","UDP:8080","UDP:9201","UDP:53","UDP:1198","UDP:1197","TCP:443","TCP:110","TCP:80","TCP:502","TCP:501"],"cipher":"AES-128-GCM","auth":"SHA1","ca":"-----BEGIN CERTIFICATE-----\nMIIFqzCCBJOgAwIBAgIJAKZ7D5Yv87qDMA0GCSqGSIb3DQEBDQUAMIHoMQswCQYD\nVQQGEwJVUzELMAkGA1UECBMCQ0ExEzARBgNVBAcTCkxvc0FuZ2VsZXMxIDAeBgNV\nBAoTF1ByaXZhdGUgSW50ZXJuZXQgQWNjZXNzMSAwHgYDVQQLExdQcml2YXRlIElu\ndGVybmV0IEFjY2VzczEgMB4GA1UEAxMXUHJpdmF0ZSBJbnRlcm5ldCBBY2Nlc3Mx\nIDAeBgNVBCkTF1ByaXZhdGUgSW50ZXJuZXQgQWNjZXNzMS8wLQYJKoZIhvcNAQkB\nFiBzZWN1cmVAcHJpdmF0ZWludGVybmV0YWNjZXNzLmNvbTAeFw0xNDA0MTcxNzM1\nMThaFw0zNDA0MTIxNzM1MThaMIHoMQswCQYDVQQGEwJVUzELMAkGA1UECBMCQ0Ex\nEzARBgNVBAcTCkxvc0FuZ2VsZXMxIDAeBgNVBAoTF1ByaXZhdGUgSW50ZXJuZXQg\nQWNjZXNzMSAwHgYDVQQLExdQcml2YXRlIEludGVybmV0IEFjY2VzczEgMB4GA1UE\nAxMXUHJpdmF0ZSBJbnRlcm5ldCBBY2Nlc3MxIDAeBgNVBCkTF1ByaXZhdGUgSW50\nZXJuZXQgQWNjZXNzMS8wLQYJKoZIhvcNAQkBFiBzZWN1cmVAcHJpdmF0ZWludGVy\nbmV0YWNjZXNzLmNvbTCCASIwDQYJKoZIhvcNAQEBBQADggEPADCCAQoCggEBAPXD\nL1L9tX6DGf36liA7UBTy5I869z0UVo3lImfOs/GSiFKPtInlesP65577nd7UNzzX\nlH/P/CnFPdBWlLp5ze3HRBCc/Avgr5CdMRkEsySL5GHBZsx6w2cayQ2EcRhVTwWp\ncdldeNO+pPr9rIgPrtXqT4SWViTQRBeGM8CDxAyTopTsobjSiYZCF9Ta1gunl0G/\n8Vfp+SXfYCC+ZzWvP+L1pFhPRqzQQ8k+wMZIovObK1s+nlwPaLyayzw9a8sUnvWB\n/5rGPdIYnQWPgoNlLN9HpSmsAcw2z8DXI9pIxbr74cb3/HSfuYGOLkRqrOk6h4RC\nOfuWoTrZup1uEOn+fw8CAwEAAaOCAVQwggFQMB0GA1UdDgQWBBQv63nQ/pJAt5tL\ny8VJcbHe22ZOsjCCAR8GA1UdIwSCARYwggESgBQv63nQ/pJAt5tLy8VJcbHe22ZO\nsqGB7qSB6zCB6DELMAkGA1UEBhMCVVMxCzAJBgNVBAgTAkNBMRMwEQYDVQQHEwpM\nb3NBbmdlbGVzMSAwHgYDVQQKExdQcml2YXRlIEludGVybmV0IEFjY2VzczEgMB4G\nA1UECxMXUHJpdmF0ZSBJbnRlcm5ldCBBY2Nlc3MxIDAeBgNVBAMTF1ByaXZhdGUg\nSW50ZXJuZXQgQWNjZXNzMSAwHgYDVQQpExdQcml2YXRlIEludGVybmV0IEFjY2Vz\nczEvMC0GCSqGSIb3DQEJARYgc2VjdXJlQHByaXZhdGVpbnRlcm5ldGFjY2Vzcy5j\nb22CCQCmew+WL/O6gzAMBgNVHRMEBTADAQH/MA0GCSqGSIb3DQEBDQUAA4IBAQAn\na5PgrtxfwTumD4+3/SYvwoD66cB8IcK//h1mCzAduU8KgUXocLx7QgJWo9lnZ8xU\nryXvWab2usg4fqk7FPi00bED4f4qVQFVfGfPZIH9QQ7/48bPM9RyfzImZWUCenK3\n7pdw4Bvgoys2rHLHbGen7f28knT2j/cbMxd78tQc20TIObGjo8+ISTRclSTRBtyC\nGohseKYpTS9himFERpUgNtefvYHbn70mIOzfOJFTVqfrptf9jXa9N8Mpy3ayfodz\n1wiqdteqFXkTYoSDctgKMiZ6GdocK9nMroQipIQtpnwd4yBDWIyC6Bvlkrq5TQUt\nYDQ8z9v+DMO6iwyIDRiU\n-----END CERTIFICATE-----\n","frame":1,"ping":10,"reneg":3600,"pia":true}},{"id":"strong","name":"Strong","comment":"256-bit encryption (slower)","cfg":{"ep":["UDP:1194","UDP:8080","UDP:9201","UDP:53","UDP:1198","UDP:1197","TCP:443","TCP:110","TCP:80","TCP:502","TCP:501"],"cipher":"AES-256-GCM","auth":"SHA256","ca":"-----BEGIN CERTIFICATE-----\nMIIHqzCCBZOgAwIBAgIJAJ0u+vODZJntMA0GCSqGSIb3DQEBDQUAMIHoMQswCQYD\nVQQGEwJVUzELMAkGA1UECBMCQ0ExEzARBgNVBAcTCkxvc0FuZ2VsZXMxIDAeBgNV\nBAoTF1ByaXZhdGUgSW50ZXJuZXQgQWNjZXNzMSAwHgYDVQQLExdQcml2YXRlIElu\ndGVybmV0IEFjY2VzczEgMB4GA1UEAxMXUHJpdmF0ZSBJbnRlcm5ldCBBY2Nlc3Mx\nIDAeBgNVBCkTF1ByaXZhdGUgSW50ZXJuZXQgQWNjZXNzMS8wLQYJKoZIhvcNAQkB\nFiBzZWN1cmVAcHJpdmF0ZWludGVybmV0YWNjZXNzLmNvbTAeFw0xNDA0MTcxNzQw\nMzNaFw0zNDA0MTIxNzQwMzNaMIHoMQswCQYDVQQGEwJVUzELMAkGA1UECBMCQ0Ex\nEzARBgNVBAcTCkxvc0FuZ2VsZXMxIDAeBgNVBAoTF1ByaXZhdGUgSW50ZXJuZXQg\nQWNjZXNzMSAwHgYDVQQLExdQcml2YXRlIEludGVybmV0IEFjY2VzczEgMB4GA1UE\nAxMXUHJpdmF0ZSBJbnRlcm5ldCBBY2Nlc3MxIDAeBgNVBCkTF1ByaXZhdGUgSW50\nZXJuZXQgQWNjZXNzMS8wLQYJKoZIhvcNAQkBFiBzZWN1cmVAcHJpdmF0ZWludGVy\nbmV0YWNjZXNzLmNvbTCCAiIwDQYJKoZIhvcNAQEBBQADggIPADCCAgoCggIBALVk\nhjumaqBbL8aSgj6xbX1QPTfTd1qHsAZd2B97m8Vw31c/2yQgZNf5qZY0+jOIHULN\nDe4R9TIvyBEbvnAg/OkPw8n/+ScgYOeH876VUXzjLDBnDb8DLr/+w9oVsuDeFJ9K\nV2UFM1OYX0SnkHnrYAN2QLF98ESK4NCSU01h5zkcgmQ+qKSfA9Ny0/UpsKPBFqsQ\n25NvjDWFhCpeqCHKUJ4Be27CDbSl7lAkBuHMPHJs8f8xPgAbHRXZOxVCpayZ2SND\nfCwsnGWpWFoMGvdMbygngCn6jA/W1VSFOlRlfLuuGe7QFfDwA0jaLCxuWt/BgZyl\np7tAzYKR8lnWmtUCPm4+BtjyVDYtDCiGBD9Z4P13RFWvJHw5aapx/5W/CuvVyI7p\nKwvc2IT+KPxCUhH1XI8ca5RN3C9NoPJJf6qpg4g0rJH3aaWkoMRrYvQ+5PXXYUzj\ntRHImghRGd/ydERYoAZXuGSbPkm9Y/p2X8unLcW+F0xpJD98+ZI+tzSsI99Zs5wi\njSUGYr9/j18KHFTMQ8n+1jauc5bCCegN27dPeKXNSZ5riXFL2XX6BkY68y58UaNz\nmeGMiUL9BOV1iV+PMb7B7PYs7oFLjAhh0EdyvfHkrh/ZV9BEhtFa7yXp8XR0J6vz\n1YV9R6DYJmLjOEbhU8N0gc3tZm4Qz39lIIG6w3FDAgMBAAGjggFUMIIBUDAdBgNV\nHQ4EFgQUrsRtyWJftjpdRM0+925Y6Cl08SUwggEfBgNVHSMEggEWMIIBEoAUrsRt\nyWJftjpdRM0+925Y6Cl08SWhge6kgeswgegxCzAJBgNVBAYTAlVTMQswCQYDVQQI\nEwJDQTETMBEGA1UEBxMKTG9zQW5nZWxlczEgMB4GA1UEChMXUHJpdmF0ZSBJbnRl\ncm5ldCBBY2Nlc3MxIDAeBgNVBAsTF1ByaXZhdGUgSW50ZXJuZXQgQWNjZXNzMSAw\nHgYDVQQDExdQcml2YXRlIEludGVybmV0IEFjY2VzczEgMB4GA1UEKRMXUHJpdmF0\nZSBJbnRlcm5ldCBBY2Nlc3MxLzAtBgkqhkiG9w0BCQEWIHNlY3VyZUBwcml2YXRl\naW50ZXJuZXRhY2Nlc3MuY29tggkAnS7684Nkme0wDAYDVR0TBAUwAwEB/zANBgkq\nhkiG9w0BAQ0FAAOCAgEAJsfhsPk3r8kLXLxY+v+vHzbr4ufNtqnL9/1Uuf8NrsCt\npXAoyZ0YqfbkWx3NHTZ7OE9ZRhdMP/RqHQE1p4N4Sa1nZKhTKasV6KhHDqSCt/dv\nEm89xWm2MVA7nyzQxVlHa9AkcBaemcXEiyT19XdpiXOP4Vhs+J1R5m8zQOxZlV1G\ntF9vsXmJqWZpOVPmZ8f35BCsYPvv4yMewnrtAC8PFEK/bOPeYcKN50bol22QYaZu\nLfpkHfNiFTnfMh8sl/ablPyNY7DUNiP5DRcMdIwmfGQxR5WEQoHL3yPJ42LkB5zs\n6jIm26DGNXfwura/mi105+ENH1CaROtRYwkiHb08U6qLXXJz80mWJkT90nr8Asj3\n5xN2cUppg74nG3YVav/38P48T56hG1NHbYF5uOCske19F6wi9maUoto/3vEr0rnX\nJUp2KODmKdvBI7co245lHBABWikk8VfejQSlCtDBXn644ZMtAdoxKNfR2WTFVEwJ\niyd1Fzx0yujuiXDROLhISLQDRjVVAvawrAtLZWYK31bY7KlezPlQnl/D9Asxe85l\n8jO5+0LdJ6VyOs/Hd4w52alDW/MFySDZSfQHMTIc30hLBJ8OnCEIvluVQQ2UQvoW\n+no177N9L2Y+M9TcTA62ZyMXShHQGeh20rb4kK8f+iFX8NxtdHVSkxMEFSfDDyQ=\n-----END CERTIFICATE-----\n","frame":1,"ping":10,"reneg":3600,"pia":true}}],"defaults":{"username":"p1234567","pool":"us-east","preset":"recommended"}}

